eyed3/__about__.pyi
eyed3/__init__.pyi
eyed3/__regarding__.pyi
eyed3/core.pyi
eyed3/mimetype.pyi
eyed3/id3/__init__.pyi
eyed3/id3/apple.pyi
eyed3/id3/frames.pyi
eyed3/id3/headers.pyi
eyed3/id3/tag.pyi
eyed3/mp3/__init__.pyi
eyed3/mp3/headers.pyi
eyed3/plugins/__init__.pyi
eyed3/plugins/art.pyi
eyed3/plugins/classic.pyi
eyed3/plugins/extract.pyi
eyed3/plugins/fixup.pyi
eyed3/plugins/genres.pyi
eyed3/plugins/itunes.pyi
eyed3/plugins/jsontag.pyi
eyed3/plugins/lameinfo.pyi
eyed3/plugins/lastfm.pyi
eyed3/plugins/mimetype.pyi
eyed3/plugins/nfo.pyi
eyed3/plugins/pymod.pyi
eyed3/plugins/stats.pyi
eyed3/plugins/xep_118.pyi
eyed3/plugins/yamltag.pyi
eyed3/utils/__init__.pyi
eyed3/utils/art.pyi
eyed3/utils/binfuncs.pyi
eyed3/utils/console.pyi
eyed3/utils/prompt.pyi
types_eyed3-0.9.7.20250306.dist-info/METADATA
types_eyed3-0.9.7.20250306.dist-info/WHEEL
types_eyed3-0.9.7.20250306.dist-info/top_level.txt
types_eyed3-0.9.7.20250306.dist-info/RECORD
