Metadata-Version: 2.2
Name: types-eyed3
Version: 0.9.7.20250306
Summary: Type hints for the eyed3 library
Requires-Python: >=3.12
